LICENSE
MANIFEST.in
README.md
README.rst
setup.py
django_google_auth.egg-info/PKG-INFO
django_google_auth.egg-info/SOURCES.txt
django_google_auth.egg-info/dependency_links.txt
django_google_auth.egg-info/not-zip-safe
django_google_auth.egg-info/requires.txt
django_google_auth.egg-info/top_level.txt
google_auth/__init__.py
google_auth/admin.py
google_auth/authentication.py
google_auth/models.py
google_auth/urls.py
google_auth/views.py
google_auth/migrations/0001_initial.py
google_auth/migrations/0002_auto_20170904_2225.py
google_auth/migrations/0003_googleauthuser_app_token.py
google_auth/migrations/__init__.py