Metadata-Version: 1.1
Name: django-google-auth
Version: 0.3.0
Summary: google-auth support for django
Home-page: https://github.com/felipejfc/django-google-auth
Author: Felipe Cavalcanti
Author-email: fjfcavalcanti@gmail.com
License: MIT
Platform: UNKNOWN
Classifier: Environment :: Web Environment
Classifier: Framework :: Django
Classifier: License :: OSI Approved :: MIT License
Classifier: Programming Language :: Python :: 3
